[
  {
    "companyId": "61eb650e-40db-4a18-8053-06828e06a452",
    "companyName": "Emmerich, Macejkovic and Haag",
    "catchPhrase": "Exclusive optimal open architecture",
    "buzzPhrase": "transition holistic interfaces",
    "established": "1937-06-16T07:03:14.132Z",
    "registeredAt": "2025-03-27T07:50:49.749Z"
  },
  {
    "companyId": "46a89126-3a05-4088-b460-8c5e7afda6f0",
    "companyName": "Flatley - Jenkins",
    "catchPhrase": "Triple-buffered client-driven neural-net",
    "buzzPhrase": "morph proactive initiatives",
    "established": "1947-06-19T23:34:56.914Z",
    "registeredAt": "2025-08-24T02:50:14.889Z"
  },
  {
    "companyId": "753e6d2c-1baa-43ad-8e92-be88aa80e5ff",
    "companyName": "Gibson, Kovacek and Casper",
    "catchPhrase": "Cloned discrete focus group",
    "buzzPhrase": "monetize world-class channels",
    "established": "1995-12-16T16:08:11.172Z",
    "registeredAt": "2025-04-18T18:26:12.405Z"
  },
  {
    "companyId": "8b150de1-4b3d-4d04-982a-39acf77c058a",
    "companyName": "Volkman - Zemlak",
    "catchPhrase": "Optimized systemic firmware",
    "buzzPhrase": "matrix distributed partnerships",
    "established": "1994-06-25T17:49:24.973Z",
    "registeredAt": "2025-07-30T23:43:46.239Z"
  },
  {
    "companyId": "9eca78ae-1c01-47b9-96d9-e2021691f5b8",
    "companyName": "Roob and Sons",
    "catchPhrase": "Integrated hybrid knowledge user",
    "buzzPhrase": "aggregate wireless markets",
    "established": "1974-09-25T03:51:33.496Z",
    "registeredAt": "2025-07-08T15:56:54.234Z"
  }
]
