[
  {
    "companyId": "2ef6252b-9d99-4a34-92d4-2b1e7629b602",
    "companyName": "Nicolas Group",
    "catchPhrase": "Progressive contextually-based infrastructure",
    "buzzPhrase": "incentivize B2C mindshare",
    "established": "1950-09-25T17:32:09.699Z",
    "registeredAt": "2025-04-25T07:26:31.063Z"
  },
  {
    "companyId": "58055ea8-842b-418b-b7dd-9b6898d2ca54",
    "companyName": "Collier, Romaguera and Abbott",
    "catchPhrase": "Organic global framework",
    "buzzPhrase": "monetize B2C networks",
    "established": "2013-07-28T05:20:52.917Z",
    "registeredAt": "2025-04-26T18:43:31.839Z"
  },
  {
    "companyId": "a4aaf343-d710-4a2b-b6b5-6837af19c336",
    "companyName": "Borer - Nolan",
    "catchPhrase": "Intuitive 4th generation adapter",
    "buzzPhrase": "extend efficient ROI",
    "established": "1959-05-28T01:16:25.720Z",
    "registeredAt": "2025-07-26T17:28:01.689Z"
  },
  {
    "companyId": "cd7c4f13-efd1-40ad-b361-1e6b0b6dd69f",
    "companyName": "VonRueden, Pacocha and Balistreri",
    "catchPhrase": "Multi-lateral high-level policy",
    "buzzPhrase": "reintermediate holistic web services",
    "established": "1995-05-16T14:00:12.702Z",
    "registeredAt": "2025-10-15T22:16:46.099Z"
  },
  {
    "companyId": "c08c7c69-7cb5-4f4b-805c-fad43d341d19",
    "companyName": "Terry - Moen",
    "catchPhrase": "Balanced upward-trending Graphic Interface",
    "buzzPhrase": "exploit virtual mindshare",
    "established": "2000-02-09T19:25:03.911Z",
    "registeredAt": "2026-02-02T23:55:21.691Z"
  },
  {
    "companyId": "7cdaccc0-cd15-47a0-98a9-0cfe4b5d17fb",
    "companyName": "Bins, Aufderhar and Lang",
    "catchPhrase": "Proactive asymmetric installation",
    "buzzPhrase": "recontextualize cutting-edge e-markets",
    "established": "2019-06-10T15:53:59.421Z",
    "registeredAt": "2025-10-16T11:25:53.272Z"
  },
  {
    "companyId": "65e4f45f-d7c6-4bed-bd9c-471ab4129643",
    "companyName": "Smith and Sons",
    "catchPhrase": "Cross-group content-based alliance",
    "buzzPhrase": "transition scalable metrics",
    "established": "1986-04-10T00:18:49.826Z",
    "registeredAt": "2026-03-11T18:48:42.860Z"
  }
]
