[
  {
    "companyId": "8722cc91-c9b5-4561-aeea-bc55dc753222",
    "companyName": "Maggio, Kihn and Streich",
    "catchPhrase": "Upgradable analyzing benchmark",
    "buzzPhrase": "exploit rich web services",
    "established": "1960-09-25T19:36:17.005Z",
    "registeredAt": "2025-08-12T16:26:49.816Z"
  },
  {
    "companyId": "df7c462a-f8f1-44ec-ac53-41b6bbef8d60",
    "companyName": "Cassin Inc",
    "catchPhrase": "Compatible multi-tasking hardware",
    "buzzPhrase": "enable innovative blockchains",
    "established": "2009-02-05T07:11:09.941Z",
    "registeredAt": "2025-12-30T19:39:21.732Z"
  },
  {
    "companyId": "606662f7-c4a9-4858-bbd5-e2233e37c29f",
    "companyName": "Jacobson, Luettgen and Kerluke",
    "catchPhrase": "Enhanced dedicated framework",
    "buzzPhrase": "reintermediate 24/7 blockchains",
    "established": "1951-10-29T03:25:34.948Z",
    "registeredAt": "2025-12-12T10:48:11.694Z"
  },
  {
    "companyId": "9d9b7f74-7384-4fdb-b85d-ec28c3b1b319",
    "companyName": "Williamson, McClure and Bosco",
    "catchPhrase": "Expanded full-range attitude",
    "buzzPhrase": "morph e-business networks",
    "established": "1936-01-03T02:33:58.140Z",
    "registeredAt": "2025-07-30T15:22:14.998Z"
  },
  {
    "companyId": "aebd0ff0-05af-4975-985c-44d9cde07a73",
    "companyName": "Rosenbaum, Hilpert and Mitchell",
    "catchPhrase": "Ergonomic foreground emulation",
    "buzzPhrase": "whiteboard wireless applications",
    "established": "1965-11-19T12:16:52.540Z",
    "registeredAt": "2025-07-24T08:56:35.662Z"
  },
  {
    "companyId": "3727cac0-a465-4619-a3e1-c9206b4c8bfa",
    "companyName": "Armstrong, Murray and Stracke",
    "catchPhrase": "Synchronised 6th generation definition",
    "buzzPhrase": "engage wireless architectures",
    "established": "2023-09-04T08:47:52.151Z",
    "registeredAt": "2026-02-25T22:11:43.082Z"
  },
  {
    "companyId": "b6cd3267-fdce-4cd7-898c-9b5fb19653ea",
    "companyName": "Wunsch, Denesik and Conn",
    "catchPhrase": "Multi-layered intangible access",
    "buzzPhrase": "synergize proactive ROI",
    "established": "2005-08-15T20:26:37.736Z",
    "registeredAt": "2025-07-05T04:19:08.493Z"
  }
]
