[
  {
    "companyId": "1bb8abd2-0352-42e8-bb34-53b97b121e39",
    "companyName": "Farrell - Haley",
    "catchPhrase": "Persevering composite migration",
    "buzzPhrase": "integrate synergistic communities",
    "established": "1956-03-26T04:12:48.190Z",
    "registeredAt": "2026-03-07T15:46:21.862Z"
  },
  {
    "companyId": "340c9bd8-4f31-416e-bf7b-aa39d6e42efd",
    "companyName": "Feest, Bogisich and Gislason",
    "catchPhrase": "Mandatory interactive synergy",
    "buzzPhrase": "leverage enterprise markets",
    "established": "2017-11-25T15:45:13.843Z",
    "registeredAt": "2025-08-05T07:00:48.133Z"
  },
  {
    "companyId": "4da487b3-4692-4995-b054-7b5163e247d5",
    "companyName": "Grady - Haley",
    "catchPhrase": "Upgradable multi-state focus group",
    "buzzPhrase": "synergize vertical initiatives",
    "established": "1970-04-23T11:13:13.612Z",
    "registeredAt": "2025-04-04T03:12:02.097Z"
  },
  {
    "companyId": "66bc3e8f-1505-41eb-9598-f0d932a421fd",
    "companyName": "Hayes - Hudson",
    "catchPhrase": "Reactive 5th generation benchmark",
    "buzzPhrase": "seize real-time mindshare",
    "established": "1938-09-17T11:17:09.594Z",
    "registeredAt": "2026-02-13T02:57:22.357Z"
  },
  {
    "companyId": "680db1c6-5a29-44ed-9d98-4d02e090eefc",
    "companyName": "Hyatt - Purdy",
    "catchPhrase": "Synergistic scalable software",
    "buzzPhrase": "grow scalable convergence",
    "established": "1995-12-02T13:47:11.771Z",
    "registeredAt": "2025-05-20T01:56:08.353Z"
  }
]
