[
  {
    "companyId": "85bf427a-fd55-4b31-8dc5-146ad89268dd",
    "companyName": "Homenick - Swift",
    "catchPhrase": "Reduced didactic array",
    "buzzPhrase": "synthesize cross-platform platforms",
    "established": "1955-12-04T18:36:30.407Z",
    "registeredAt": "2025-10-04T10:28:22.756Z"
  },
  {
    "companyId": "eae60971-ce35-45e1-adc4-97e888565e3c",
    "companyName": "Reichel Inc",
    "catchPhrase": "Seamless value-added system engine",
    "buzzPhrase": "evolve B2C methodologies",
    "established": "2002-05-14T08:51:20.423Z",
    "registeredAt": "2025-08-14T08:05:02.372Z"
  },
  {
    "companyId": "0acc3e01-7b68-4f8d-9b7c-65bfb22d029e",
    "companyName": "Kshlerin LLC",
    "catchPhrase": "Streamlined bottom-line adapter",
    "buzzPhrase": "facilitate front-end convergence",
    "established": "2006-08-20T19:04:13.177Z",
    "registeredAt": "2025-10-17T06:00:23.336Z"
  },
  {
    "companyId": "ccc7adef-dbd5-4f15-95a7-f6d3a6a26185",
    "companyName": "Kautzer, Monahan and Kassulke",
    "catchPhrase": "Synergized regional capability",
    "buzzPhrase": "deploy cross-media schemas",
    "established": "1938-02-09T11:34:30.088Z",
    "registeredAt": "2025-06-25T11:32:56.324Z"
  },
  {
    "companyId": "2b0dbfc5-7bed-44d5-b797-7088005684ef",
    "companyName": "Runolfsdottir Group",
    "catchPhrase": "Inverse stable website",
    "buzzPhrase": "productize viral partnerships",
    "established": "1998-12-28T00:03:41.908Z",
    "registeredAt": "2026-01-18T23:50:44.977Z"
  },
  {
    "companyId": "586892b3-e98b-4b22-987f-29d6fa9e98b8",
    "companyName": "Jacobs - Adams",
    "catchPhrase": "Switchable non-volatile utilisation",
    "buzzPhrase": "enhance seamless models",
    "established": "1987-02-18T09:31:27.387Z",
    "registeredAt": "2025-06-25T16:06:32.306Z"
  },
  {
    "companyId": "42691c35-6652-4167-928c-24c67d52c5ca",
    "companyName": "Sauer - Marks",
    "catchPhrase": "Upgradable actuating strategy",
    "buzzPhrase": "seize ubiquitous applications",
    "established": "2014-01-06T15:20:40.172Z",
    "registeredAt": "2025-05-19T04:29:21.935Z"
  },
  {
    "companyId": "1a25f8d2-1001-4b9f-b491-230cb01b185b",
    "companyName": "Nolan Group",
    "catchPhrase": "Advanced modular Graphical User Interface",
    "buzzPhrase": "leverage impactful mindshare",
    "established": "1997-05-01T11:46:46.362Z",
    "registeredAt": "2025-09-07T00:14:07.470Z"
  },
  {
    "companyId": "b4dc351d-1490-4da4-833f-b236372ddbf8",
    "companyName": "Gusikowski Inc",
    "catchPhrase": "Expanded empowering pricing structure",
    "buzzPhrase": "scale sexy metrics",
    "established": "2010-02-24T19:14:13.459Z",
    "registeredAt": "2025-09-20T20:46:46.208Z"
  },
  {
    "companyId": "fe73066d-6436-4be2-9d95-c40f17d529fb",
    "companyName": "Johns - Sipes",
    "catchPhrase": "Decentralized coherent implementation",
    "buzzPhrase": "enhance rich functionalities",
    "established": "1949-04-04T21:02:39.346Z",
    "registeredAt": "2025-06-12T09:44:28.249Z"
  },
  {
    "companyId": "636c5977-e315-4428-8ef5-5df77760e0a0",
    "companyName": "Cruickshank, Yost and Kuvalis",
    "catchPhrase": "User-friendly zero administration local area network",
    "buzzPhrase": "redefine customized synergies",
    "established": "1934-05-08T13:29:52.718Z",
    "registeredAt": "2025-09-29T22:15:03.169Z"
  },
  {
    "companyId": "f089bed8-087e-4f8f-880a-61b339289d98",
    "companyName": "Muller LLC",
    "catchPhrase": "Enhanced motivating knowledge user",
    "buzzPhrase": "whiteboard plug-and-play infrastructures",
    "established": "1985-06-25T02:53:32.318Z",
    "registeredAt": "2025-06-10T03:47:38.837Z"
  },
  {
    "companyId": "6308eec4-132f-45f4-83a2-3640bf63a52e",
    "companyName": "Kertzmann - Collier",
    "catchPhrase": "Self-enabling full-range productivity",
    "buzzPhrase": "unleash proactive content",
    "established": "1950-08-20T07:53:51.351Z",
    "registeredAt": "2025-05-10T10:13:35.870Z"
  },
  {
    "companyId": "9f0480ad-6be7-4484-bdca-6fbadcf5300c",
    "companyName": "Greenfelder, Thompson and Gottlieb",
    "catchPhrase": "Future-proofed hybrid methodology",
    "buzzPhrase": "deliver bleeding-edge interfaces",
    "established": "1948-01-27T14:31:02.734Z",
    "registeredAt": "2025-05-17T01:20:50.155Z"
  },
  {
    "companyId": "b811fdd7-b042-44f5-9460-29ea3aaebcfe",
    "companyName": "King - Hermann",
    "catchPhrase": "Centralized clear-thinking parallelism",
    "buzzPhrase": "exploit sticky content",
    "established": "2008-06-14T08:16:43.638Z",
    "registeredAt": "2025-07-09T06:50:01.341Z"
  }
]
