[
  {
    "companyId": "0ed66ace-278f-4cfb-a89b-604fd2f73599",
    "companyName": "Gerlach, Fritsch and Rolfson",
    "catchPhrase": "Customizable cohesive contingency",
    "buzzPhrase": "iterate synergistic platforms",
    "established": "1968-04-21T07:03:04.316Z",
    "registeredAt": "2025-10-25T14:41:07.255Z"
  },
  {
    "companyId": "78ee67aa-d048-43e7-9dee-fe46f2daf136",
    "companyName": "Morissette Inc",
    "catchPhrase": "Progressive bottom-line task-force",
    "buzzPhrase": "reinvent wireless initiatives",
    "established": "1969-08-22T12:25:34.722Z",
    "registeredAt": "2025-10-02T11:19:35.838Z"
  }
]
