[
  {
    "companyId": "c309649b-f45e-45be-8522-9ce52c5d52fe",
    "companyName": "Jenkins Inc",
    "catchPhrase": "Ergonomic bottom-line analyzer",
    "buzzPhrase": "generate bricks-and-clicks action-items",
    "established": "1950-01-16T21:34:55.434Z",
    "registeredAt": "2025-05-26T11:38:21.572Z"
  },
  {
    "companyId": "30b555f3-d4af-41d8-a8f0-e85b6b6aa1f4",
    "companyName": "Tremblay, Orn and Donnelly",
    "catchPhrase": "Profound content-based secured line",
    "buzzPhrase": "cultivate granular bandwidth",
    "established": "2009-12-25T15:13:08.149Z",
    "registeredAt": "2025-07-21T06:09:50.942Z"
  },
  {
    "companyId": "ba58bba5-8740-45c5-898e-ce19047df6f8",
    "companyName": "Ritchie, Heaney and Lowe",
    "catchPhrase": "Focused even-keeled superstructure",
    "buzzPhrase": "scale killer web services",
    "established": "2002-10-04T02:17:33.721Z",
    "registeredAt": "2025-09-20T12:32:03.363Z"
  },
  {
    "companyId": "f8c8c888-f26b-43b5-9120-ff92b5e11948",
    "companyName": "Considine - Waters",
    "catchPhrase": "Fully-configurable incremental protocol",
    "buzzPhrase": "benchmark dynamic blockchains",
    "established": "2018-02-27T14:37:19.808Z",
    "registeredAt": "2026-01-25T04:24:59.008Z"
  },
  {
    "companyId": "1d9d8cd9-35a1-485f-b254-1a4393e8148b",
    "companyName": "Schaefer Group",
    "catchPhrase": "Quality-focused fault-tolerant encoding",
    "buzzPhrase": "transition frictionless platforms",
    "established": "1994-09-27T01:08:24.019Z",
    "registeredAt": "2025-07-30T16:47:50.110Z"
  },
  {
    "companyId": "6aec7d41-5beb-45e3-b89b-0e925aaa73b9",
    "companyName": "King Group",
    "catchPhrase": "Front-line local open system",
    "buzzPhrase": "seize collaborative e-business",
    "established": "1986-04-22T19:45:43.065Z",
    "registeredAt": "2025-12-28T19:24:57.880Z"
  },
  {
    "companyId": "a4a165c5-5903-493e-b841-98d6e89bc222",
    "companyName": "Von - Torphy",
    "catchPhrase": "User-centric even-keeled toolset",
    "buzzPhrase": "integrate bricks-and-clicks technologies",
    "established": "1998-07-05T14:24:17.609Z",
    "registeredAt": "2025-06-08T11:51:28.856Z"
  },
  {
    "companyId": "d12fc44c-a953-40b8-a42c-d7734a303142",
    "companyName": "Raynor and Sons",
    "catchPhrase": "Programmable systematic flexibility",
    "buzzPhrase": "seize leading-edge e-markets",
    "established": "1937-10-19T01:27:33.555Z",
    "registeredAt": "2025-05-27T04:25:36.137Z"
  },
  {
    "companyId": "c9fba800-487c-4037-b92a-22b0f6e86110",
    "companyName": "Boyer LLC",
    "catchPhrase": "Seamless demand-driven projection",
    "buzzPhrase": "orchestrate bricks-and-clicks synergies",
    "established": "1967-04-23T17:02:29.970Z",
    "registeredAt": "2025-08-14T13:33:50.066Z"
  },
  {
    "companyId": "436779e0-c73d-46f9-9834-7ee2c4643d39",
    "companyName": "Paucek, Corkery and Murphy",
    "catchPhrase": "Configurable even-keeled knowledge user",
    "buzzPhrase": "grow leading-edge functionalities",
    "established": "1948-05-07T07:56:29.161Z",
    "registeredAt": "2025-09-08T13:20:42.706Z"
  },
  {
    "companyId": "6ac3cb72-407d-47ad-8da2-20312c8edbba",
    "companyName": "Armstrong - Waelchi",
    "catchPhrase": "Managed motivating analyzer",
    "buzzPhrase": "mesh bricks-and-clicks ROI",
    "established": "2002-12-24T01:39:33.476Z",
    "registeredAt": "2025-09-21T02:52:47.431Z"
  },
  {
    "companyId": "0e20a5fa-119f-450b-a377-35c76bd3095a",
    "companyName": "Turner - Lubowitz",
    "catchPhrase": "Networked upward-trending workforce",
    "buzzPhrase": "morph dynamic models",
    "established": "1991-02-18T17:42:38.468Z",
    "registeredAt": "2025-12-24T13:47:15.720Z"
  },
  {
    "companyId": "85c40d08-ae7e-4a86-8032-68197e378e84",
    "companyName": "D'Amore - Treutel",
    "catchPhrase": "Down-sized eco-centric leverage",
    "buzzPhrase": "productize back-end partnerships",
    "established": "1935-04-27T20:18:07.111Z",
    "registeredAt": "2025-06-18T05:31:23.635Z"
  },
  {
    "companyId": "cc3c4051-5433-4571-a115-63f8ab9f3be0",
    "companyName": "Rath, Lockman and Padberg",
    "catchPhrase": "Business-focused fresh-thinking Graphical User Interface",
    "buzzPhrase": "monetize out-of-the-box relationships",
    "established": "1960-09-20T18:46:00.477Z",
    "registeredAt": "2025-04-20T21:58:04.392Z"
  },
  {
    "companyId": "657dd1ef-4825-4a97-9c66-a276c43fb450",
    "companyName": "Little, Johns and Pfeffer",
    "catchPhrase": "Multi-lateral zero defect time-frame",
    "buzzPhrase": "redefine sticky e-business",
    "established": "1975-04-26T12:05:58.232Z",
    "registeredAt": "2025-09-21T15:24:37.228Z"
  },
  {
    "companyId": "d1084e0f-c083-402a-ab88-1688cc37f580",
    "companyName": "O'Connell LLC",
    "catchPhrase": "Automated interactive throughput",
    "buzzPhrase": "morph e-business portals",
    "established": "2012-01-29T23:01:47.005Z",
    "registeredAt": "2025-08-29T15:52:24.224Z"
  },
  {
    "companyId": "bc066c7d-8367-4997-a6ef-fefdf3689a21",
    "companyName": "Hessel and Sons",
    "catchPhrase": "Stand-alone bandwidth-monitored infrastructure",
    "buzzPhrase": "reintermediate granular markets",
    "established": "1932-05-31T10:23:50.400Z",
    "registeredAt": "2025-07-16T21:36:46.457Z"
  }
]
