[
  {
    "userId": "36104c34-21e3-4746-8b91-b611915a32e4",
    "fullName": "Lynda Kautzer",
    "bio": "campus junkie  🍖",
    "gender": "Cisgender female",
    "birthdate": "1959-09-29T15:41:21.816Z",
    "registeredAt": "2025-11-06T19:03:40.003Z"
  },
  {
    "userId": "94453b04-eb86-42ed-adbe-6182bc248a43",
    "fullName": "Jamie Dickinson",
    "bio": "realization supporter, nerd",
    "gender": "Transexual person",
    "birthdate": "1953-01-22T17:35:36.743Z",
    "registeredAt": "2025-07-13T00:57:27.872Z"
  }
]
