[
  {
    "userId": "9f12f534-6304-4232-a7aa-715a4fe3cc00",
    "fullName": "Dr. Elbert Mosciski",
    "bio": "traveler, writer",
    "gender": "Intersex woman",
    "birthdate": "2002-05-03T10:39:36.680Z",
    "registeredAt": "2025-10-08T13:03:11.801Z"
  },
  {
    "userId": "8c10d9f5-5332-4fb5-820e-df09985c532f",
    "fullName": "Dr. Lorenzo Rau",
    "bio": "activist",
    "gender": "Trans female",
    "birthdate": "1979-09-20T11:14:37.993Z",
    "registeredAt": "2025-10-01T05:37:05.188Z"
  },
  {
    "userId": "6af5a472-cd4e-497e-9840-9fa5367ef64a",
    "fullName": "Ann Ledner",
    "bio": "gamer, scientist, creator",
    "gender": "Neutrois",
    "birthdate": "1965-04-20T15:24:40.094Z",
    "registeredAt": "2026-02-25T05:05:53.096Z"
  },
  {
    "userId": "42d6a033-0ea0-4113-b9c9-6b675bcc8bf6",
    "fullName": "Ms. Krista Fahey",
    "bio": "issue lover  ♥️",
    "gender": "Female to male",
    "birthdate": "2007-05-28T15:55:36.309Z",
    "registeredAt": "2025-10-13T03:10:26.521Z"
  },
  {
    "userId": "c58caa83-55b1-4394-9e1c-39bd9b68ef02",
    "fullName": "Devin Koepp",
    "bio": "cocktail advocate",
    "gender": "Cisgender man",
    "birthdate": "1995-08-03T12:21:53.632Z",
    "registeredAt": "2026-01-21T23:45:29.993Z"
  }
]
