[
  {
    "userId": "f0f651fb-a711-4d56-950e-0f1cd43feb60",
    "fullName": "Juana Rippin",
    "bio": "tart supporter, developer 🎭",
    "gender": "Demi-woman",
    "birthdate": "1960-04-08T15:55:50.161Z",
    "registeredAt": "2025-09-02T13:33:33.464Z"
  },
  {
    "userId": "77836cb8-ea96-4d1f-8494-5a972626fea7",
    "fullName": "Ernestine Witting",
    "bio": "creator, business owner, developer 🇧🇶",
    "gender": "Demi-boy",
    "birthdate": "2006-01-03T20:18:07.360Z",
    "registeredAt": "2025-11-20T07:59:33.944Z"
  },
  {
    "userId": "a78b8559-1014-4427-9b79-0114ddf11b16",
    "fullName": "Doyle Davis III",
    "bio": "activist, nerd",
    "gender": "Cisgender female",
    "birthdate": "1978-09-07T14:25:06.171Z",
    "registeredAt": "2025-07-16T02:32:56.537Z"
  },
  {
    "userId": "9511fb18-8ac3-4060-820d-c4c7ea15492a",
    "fullName": "Robin Kuhic",
    "bio": "octave lover",
    "gender": "Female to male",
    "birthdate": "1988-01-19T00:15:18.773Z",
    "registeredAt": "2025-06-20T00:09:38.367Z"
  },
  {
    "userId": "6e6b7472-3cb7-42f8-b17d-d5e6b69341f9",
    "fullName": "Donnie Morar DDS",
    "bio": "fifth devotee, designer",
    "gender": "Cis woman",
    "birthdate": "1966-10-19T21:23:40.356Z",
    "registeredAt": "2025-07-21T05:38:58.307Z"
  },
  {
    "userId": "c275069c-259c-41f1-b5aa-615dc3c2271c",
    "fullName": "Israel Quigley",
    "bio": "coach, designer, teacher",
    "gender": "Intersex person",
    "birthdate": "1966-01-12T22:20:17.824Z",
    "registeredAt": "2026-03-06T15:55:46.295Z"
  },
  {
    "userId": "b6f2686a-acf5-4602-a833-1f4bf8ac58f6",
    "fullName": "Austin Carroll",
    "bio": "bond fan, creator",
    "gender": "Cis woman",
    "birthdate": "1950-05-10T10:39:35.384Z",
    "registeredAt": "2026-01-20T16:48:17.178Z"
  }
]
