[
  {
    "userId": "946baa47-33e6-4785-9b04-0a1f01bf44fe",
    "fullName": "Cody Marvin",
    "bio": "planning fan, scientist 👏🏻",
    "gender": "Gender nonconforming",
    "birthdate": "1967-08-22T13:08:30.971Z",
    "registeredAt": "2026-02-11T05:37:53.568Z"
  },
  {
    "userId": "820e01e3-808e-4eca-999e-2f0e90927b17",
    "fullName": "Jana Halvorson",
    "bio": "chalice devotee",
    "gender": "Trigender",
    "birthdate": "1959-04-07T19:54:51.098Z",
    "registeredAt": "2026-01-27T21:10:46.874Z"
  },
  {
    "userId": "3b8e19f9-ec03-494f-bc8a-cd6efdf1a4c8",
    "fullName": "Dr. Marta Weber",
    "bio": "patriot, public speaker, veteran",
    "gender": "M2F",
    "birthdate": "1957-11-07T23:14:53.861Z",
    "registeredAt": "2026-01-23T09:45:46.338Z"
  },
  {
    "userId": "e89b8a86-5a71-4490-878c-ae19b7737ae8",
    "fullName": "Mr. Hugh Carroll",
    "bio": "entrepreneur",
    "gender": "Demi-boy",
    "birthdate": "1961-10-19T08:11:23.055Z",
    "registeredAt": "2025-06-20T00:21:01.520Z"
  },
  {
    "userId": "ded5d159-d227-4b03-a885-53db998023ac",
    "fullName": "Lester Sanford",
    "bio": "hub lover, photographer",
    "gender": "Pangender",
    "birthdate": "1975-07-26T10:30:20.803Z",
    "registeredAt": "2025-06-20T12:25:11.372Z"
  },
  {
    "userId": "64a9d926-f20b-46a7-a703-e365c9c4dba9",
    "fullName": "Miss Lucy Green",
    "bio": "author, film lover, author",
    "gender": "F2M",
    "birthdate": "1948-01-29T06:01:26.206Z",
    "registeredAt": "2025-09-06T15:46:46.230Z"
  },
  {
    "userId": "edcb2cea-1e97-4983-9f98-0338f76fadd9",
    "fullName": "Bradley Rau",
    "bio": "cleft fan, scientist",
    "gender": "Male to female",
    "birthdate": "1978-12-19T13:09:08.767Z",
    "registeredAt": "2025-06-28T10:40:51.488Z"
  },
  {
    "userId": "a089f1bf-7693-41c6-aae4-ac7588e013db",
    "fullName": "Ellis Smith",
    "bio": "patriot, teacher, foodie",
    "gender": "Trans",
    "birthdate": "2007-08-08T13:29:43.779Z",
    "registeredAt": "2025-07-19T08:50:11.576Z"
  },
  {
    "userId": "e12e056e-2e20-4a24-91fe-1bda6b024add",
    "fullName": "Ruth Reichert",
    "bio": "frame devotee",
    "gender": "Transexual man",
    "birthdate": "1966-11-15T21:07:41.785Z",
    "registeredAt": "2026-02-01T12:00:16.616Z"
  },
  {
    "userId": "fd6b7b43-5c3f-4deb-99a0-04c940af1282",
    "fullName": "Shelley Parker",
    "bio": "photographer, musician, leader",
    "gender": "Female to male transsexual man",
    "birthdate": "1981-10-13T09:58:13.444Z",
    "registeredAt": "2026-02-04T13:20:54.721Z"
  },
  {
    "userId": "773f05b6-e270-4afd-b59a-1d6454d42e7a",
    "fullName": "Sergio Dare",
    "bio": "litigation devotee  🐥",
    "gender": "Female to male",
    "birthdate": "1976-05-26T04:16:08.824Z",
    "registeredAt": "2025-05-24T17:53:27.061Z"
  },
  {
    "userId": "a44fe349-e7f8-4bc0-b29b-afe174bbd2f7",
    "fullName": "Darren Koelpin III",
    "bio": "developer, geek, patriot",
    "gender": "Transgender person",
    "birthdate": "1991-06-14T09:44:43.613Z",
    "registeredAt": "2025-07-04T23:28:53.368Z"
  }
]
