[
  {
    "userId": "8953486e-02f7-4f97-9bfa-8c150dfe70c4",
    "fullName": "Kari Fadel",
    "bio": "fitness advocate",
    "gender": "Gender questioning",
    "birthdate": "1950-03-17T13:25:11.495Z",
    "registeredAt": "2023-07-02T12:33:52.678Z"
  },
  {
    "userId": "03e1586c-6ebd-49a2-ada5-715e9bdb97d6",
    "fullName": "Joyce Funk",
    "bio": "patriot, film lover, veteran",
    "gender": "Agender",
    "birthdate": "2004-12-20T12:54:51.717Z",
    "registeredAt": "2024-02-16T23:32:45.796Z"
  },
  {
    "userId": "1af2f842-1b5c-4a99-b95b-026009f369f8",
    "fullName": "Miss Sharon Boyer",
    "bio": "leader",
    "gender": "M2F",
    "birthdate": "1968-04-27T17:10:57.522Z",
    "registeredAt": "2023-05-03T09:09:50.234Z"
  },
  {
    "userId": "8a569208-de25-497b-8bc7-f8c7e146596d",
    "fullName": "Dr. Sam Crona",
    "bio": "envelope advocate, film lover 🐚",
    "gender": "Demi-girl",
    "birthdate": "1971-11-30T16:48:17.292Z",
    "registeredAt": "2023-08-01T21:58:47.344Z"
  },
  {
    "userId": "5782f468-8711-40bc-861b-9fe50d868fa7",
    "fullName": "Salvador Kunze",
    "bio": "sunbeam junkie",
    "gender": "Trans female",
    "birthdate": "1974-07-31T10:50:42.433Z",
    "registeredAt": "2023-11-25T12:50:06.925Z"
  },
  {
    "userId": "624f9b4d-bb62-4500-97e1-316689f5b065",
    "fullName": "Mr. Abraham Upton",
    "bio": "founder, streamer",
    "gender": "Cis male",
    "birthdate": "1983-02-01T09:28:04.045Z",
    "registeredAt": "2023-07-10T07:39:19.773Z"
  },
  {
    "userId": "6086a684-6c00-47cf-9c4f-de47462cb5c5",
    "fullName": "Jeffery Morar",
    "bio": "connotation supporter  🎛️",
    "gender": "Cisgender female",
    "birthdate": "1955-05-21T15:49:59.583Z",
    "registeredAt": "2023-11-04T14:53:18.632Z"
  },
  {
    "userId": "bde3c1e0-8483-4cf3-86d1-5ce0b7557ba4",
    "fullName": "Max Conn",
    "bio": "geek, film lover",
    "gender": "Trans female",
    "birthdate": "1991-01-07T09:18:28.105Z",
    "registeredAt": "2023-08-30T00:56:32.624Z"
  },
  {
    "userId": "312cac86-2120-4a2f-b5f9-7eb9ffa88e7e",
    "fullName": "Chester Schaefer",
    "bio": "singer, musician, entrepreneur",
    "gender": "Neither",
    "birthdate": "1976-12-07T23:42:41.428Z",
    "registeredAt": "2024-01-28T20:56:57.957Z"
  }
]