[
  {
    "productId": "e0c4ff39-8607-4bed-9c3b-250779ef5d29",
    "productName": "Unbranded Fresh Sausages",
    "price": "284.00",
    "productDescription": "The Nagasaki Lander is the trademarked name of several series of Nagasaki sport bikes, that started with the 1984 ABC800J",
    "registeredAt": "2025-09-24T15:11:40.069Z"
  },
  {
    "productId": "8ae9b990-59b3-4a2e-91ab-af76e0a456e6",
    "productName": "Ergonomic Wooden Tuna",
    "price": "354.00",
    "productDescription": "Carbonite web goalkeeper gloves are ergonomically designed to give easy fit",
    "registeredAt": "2025-09-05T03:29:57.553Z"
  }
]
