[
  {
    "productId": "5e0c1f77-75c1-430f-9a01-8e3e63466b36",
    "productName": "Practical Granite Cheese",
    "price": "259.00",
    "productDescription": "Andy shoes are designed to keeping in mind durability as well as trends, the most stylish range of shoes & sandals",
    "registeredAt": "2025-03-21T23:21:31.041Z"
  },
  {
    "productId": "f5628117-6175-4eca-be37-bd0ee6a64bac",
    "productName": "Handmade Wooden Sausages",
    "price": "305.00",
    "productDescription": "Carbonite web goalkeeper gloves are ergonomically designed to give easy fit",
    "registeredAt": "2026-02-15T19:53:21.538Z"
  },
  {
    "productId": "a6b64466-945d-4abb-b32e-cddecc20f740",
    "productName": "Luxurious Granite Chair",
    "price": "971.00",
    "productDescription": "The automobile layout consists of a front-engine design, with transaxle-type transmissions mounted at the rear of the engine and four wheel drive",
    "registeredAt": "2026-02-04T18:47:39.711Z"
  },
  {
    "productId": "07ed79ce-ec54-4c0d-b3b0-1ae6b65d4cc0",
    "productName": "Recycled Bronze Towels",
    "price": "82.00",
    "productDescription": "The Apollotech B340 is an affordable wireless mouse with reliable connectivity, 12 months battery life and modern design",
    "registeredAt": "2025-05-30T15:11:46.049Z"
  },
  {
    "productId": "a057fdc9-9a35-4f0b-a64a-45b727af4702",
    "productName": "Intelligent Soft Cheese",
    "price": "550.00",
    "productDescription": "The Apollotech B340 is an affordable wireless mouse with reliable connectivity, 12 months battery life and modern design",
    "registeredAt": "2025-12-06T02:00:05.178Z"
  },
  {
    "productId": "b85cce5f-b11f-48fb-8ad6-a8199e6de4a0",
    "productName": "Modern Plastic Salad",
    "price": "935.00",
    "productDescription": "The automobile layout consists of a front-engine design, with transaxle-type transmissions mounted at the rear of the engine and four wheel drive",
    "registeredAt": "2026-02-13T19:00:48.965Z"
  },
  {
    "productId": "72d051be-0b6f-45c3-8013-7f5d0b010d6e",
    "productName": "Awesome Metal Chips",
    "price": "654.00",
    "productDescription": "The Football Is Good For Training And Recreational Purposes",
    "registeredAt": "2025-11-22T09:31:19.285Z"
  }
]
