[
  {
    "productId": "aed23f2b-96ab-4679-8c7e-938e9498a3f6",
    "productName": "Fantastic Fresh Sausages",
    "price": "411.00",
    "productDescription": "The Football Is Good For Training And Recreational Purposes",
    "registeredAt": "2025-07-04T10:22:48.806Z"
  },
  {
    "productId": "373f7897-79f2-43dd-a173-9bbc787cfafd",
    "productName": "Generic Wooden Gloves",
    "price": "398.00",
    "productDescription": "The Apollotech B340 is an affordable wireless mouse with reliable connectivity, 12 months battery life and modern design",
    "registeredAt": "2025-07-01T05:20:44.420Z"
  },
  {
    "productId": "9fc0e56c-9db0-414b-9473-0a70998b7b7d",
    "productName": "Rustic Bronze Shirt",
    "price": "674.00",
    "productDescription": "Andy shoes are designed to keeping in mind durability as well as trends, the most stylish range of shoes & sandals",
    "registeredAt": "2025-04-26T13:15:57.689Z"
  },
  {
    "productId": "faa592aa-0218-4620-aadd-9c4b492a9691",
    "productName": "Incredible Steel Soap",
    "price": "187.00",
    "productDescription": "The slim & simple Maple Gaming Keyboard from Dev Byte comes with a sleek body and 7- Color RGB LED Back-lighting for smart functionality",
    "registeredAt": "2025-07-03T06:50:03.385Z"
  }
]
