[
  {
    "productId": "d8228023-9a80-405a-b2c0-571ede2ac619",
    "productName": "Refined Rubber Ball",
    "price": "897.00",
    "productDescription": "The beautiful range of Apple Naturalé that has an exciting mix of natural ingredients. With the Goodness of 100% Natural Ingredients",
    "registeredAt": "2025-10-15T03:32:19.039Z"
  },
  {
    "productId": "875be511-9a7a-4fe4-8a25-09a97ae27e38",
    "productName": "Awesome Wooden Towels",
    "price": "969.00",
    "productDescription": "New ABC 13 9370, 13.3, 5th Gen CoreA5-8250U, 8GB RAM, 256GB SSD, power UHD Graphics, OS 10 Home, OS Office A & J 2016",
    "registeredAt": "2025-11-26T11:05:43.040Z"
  },
  {
    "productId": "81974283-45d7-4112-8034-c7be7ce4b99b",
    "productName": "Elegant Wooden Ball",
    "price": "988.00",
    "productDescription": "Carbonite web goalkeeper gloves are ergonomically designed to give easy fit",
    "registeredAt": "2026-02-13T00:04:20.959Z"
  },
  {
    "productId": "12a04c38-f8b7-4421-9f49-cdf2e9a34741",
    "productName": "Practical Rubber Computer",
    "price": "919.00",
    "productDescription": "The beautiful range of Apple Naturalé that has an exciting mix of natural ingredients. With the Goodness of 100% Natural Ingredients",
    "registeredAt": "2025-11-22T13:12:28.092Z"
  },
  {
    "productId": "e4dceb5f-f2d9-4df8-b4c9-b0ae023878ab",
    "productName": "Generic Frozen Chair",
    "price": "282.00",
    "productDescription": "The automobile layout consists of a front-engine design, with transaxle-type transmissions mounted at the rear of the engine and four wheel drive",
    "registeredAt": "2025-09-13T00:14:43.183Z"
  },
  {
    "productId": "a7b9d979-3b00-4191-95ed-055171d8882d",
    "productName": "Rustic Wooden Fish",
    "price": "763.00",
    "productDescription": "Carbonite web goalkeeper gloves are ergonomically designed to give easy fit",
    "registeredAt": "2026-03-04T03:48:03.449Z"
  },
  {
    "productId": "1dca46e6-8ebf-47a6-bb5c-0851bfad06ea",
    "productName": "Awesome Wooden Shoes",
    "price": "141.00",
    "productDescription": "The beautiful range of Apple Naturalé that has an exciting mix of natural ingredients. With the Goodness of 100% Natural Ingredients",
    "registeredAt": "2025-12-29T16:40:45.722Z"
  },
  {
    "productId": "c1de1038-fbd2-4f9f-b6af-e452d9a62687",
    "productName": "Bespoke Wooden Tuna",
    "price": "523.00",
    "productDescription": "The slim & simple Maple Gaming Keyboard from Dev Byte comes with a sleek body and 7- Color RGB LED Back-lighting for smart functionality",
    "registeredAt": "2025-04-10T18:19:24.262Z"
  },
  {
    "productId": "ac16e381-4cc5-4c7f-8c3a-141cec4e72ae",
    "productName": "Gorgeous Bronze Salad",
    "price": "250.00",
    "productDescription": "The Nagasaki Lander is the trademarked name of several series of Nagasaki sport bikes, that started with the 1984 ABC800J",
    "registeredAt": "2025-12-04T16:23:14.669Z"
  },
  {
    "productId": "15552ac8-c798-40d6-b4d2-b0d3073e83f2",
    "productName": "Unbranded Rubber Computer",
    "price": "902.00",
    "productDescription": "New ABC 13 9370, 13.3, 5th Gen CoreA5-8250U, 8GB RAM, 256GB SSD, power UHD Graphics, OS 10 Home, OS Office A & J 2016",
    "registeredAt": "2025-12-23T09:59:46.129Z"
  },
  {
    "productId": "374b6a9e-4c9b-479b-984d-48798d5605bf",
    "productName": "Licensed Granite Bike",
    "price": "2.00",
    "productDescription": "The Nagasaki Lander is the trademarked name of several series of Nagasaki sport bikes, that started with the 1984 ABC800J",
    "registeredAt": "2025-12-15T09:03:47.505Z"
  },
  {
    "productId": "d11ec626-f0dd-4303-9131-674e42c21e32",
    "productName": "Electronic Concrete Gloves",
    "price": "669.00",
    "productDescription": "The Football Is Good For Training And Recreational Purposes",
    "registeredAt": "2025-04-02T02:28:26.119Z"
  },
  {
    "productId": "816de965-5983-4ccb-a87d-cefeb3e4e5d2",
    "productName": "Refined Rubber Chair",
    "price": "492.00",
    "productDescription": "New ABC 13 9370, 13.3, 5th Gen CoreA5-8250U, 8GB RAM, 256GB SSD, power UHD Graphics, OS 10 Home, OS Office A & J 2016",
    "registeredAt": "2026-02-08T14:33:01.759Z"
  },
  {
    "productId": "19effdb1-67e4-49a3-8da8-f3810b31b1d9",
    "productName": "Gorgeous Plastic Sausages",
    "price": "966.00",
    "productDescription": "New ABC 13 9370, 13.3, 5th Gen CoreA5-8250U, 8GB RAM, 256GB SSD, power UHD Graphics, OS 10 Home, OS Office A & J 2016",
    "registeredAt": "2025-10-08T17:42:59.979Z"
  },
  {
    "productId": "1a10861e-635c-4820-a1c3-6aa537637742",
    "productName": "Small Steel Fish",
    "price": "702.00",
    "productDescription": "The automobile layout consists of a front-engine design, with transaxle-type transmissions mounted at the rear of the engine and four wheel drive",
    "registeredAt": "2025-05-31T12:27:44.366Z"
  },
  {
    "productId": "bd884915-48c5-43a6-8f4a-921ac39b5a3f",
    "productName": "Generic Bronze Hat",
    "price": "946.00",
    "productDescription": "The slim & simple Maple Gaming Keyboard from Dev Byte comes with a sleek body and 7- Color RGB LED Back-lighting for smart functionality",
    "registeredAt": "2025-12-31T21:33:48.140Z"
  }
]
