[
  {
    "productId": "bad12ccd-5f03-4ebf-a427-ec8a86830ba9",
    "productName": "Rustic Granite Table",
    "price": "689.00",
    "productDescription": "Carbonite web goalkeeper gloves are ergonomically designed to give easy fit",
    "registeredAt": "2025-10-27T16:52:14.063Z"
  },
  {
    "productId": "c9d558a7-f660-4fe3-b2eb-edfabd6d5ac1",
    "productName": "Generic Frozen Table",
    "price": "982.00",
    "productDescription": "The slim & simple Maple Gaming Keyboard from Dev Byte comes with a sleek body and 7- Color RGB LED Back-lighting for smart functionality",
    "registeredAt": "2025-11-14T03:37:31.937Z"
  },
  {
    "productId": "2855ebd9-121e-495a-8839-90a508a02021",
    "productName": "Oriental Rubber Shoes",
    "price": "256.00",
    "productDescription": "The automobile layout consists of a front-engine design, with transaxle-type transmissions mounted at the rear of the engine and four wheel drive",
    "registeredAt": "2025-07-23T18:58:40.484Z"
  },
  {
    "productId": "318a06ce-43c2-42b2-90f1-cdeaa381b3b8",
    "productName": "Unbranded Plastic Keyboard",
    "price": "692.00",
    "productDescription": "The Football Is Good For Training And Recreational Purposes",
    "registeredAt": "2025-08-18T07:52:48.647Z"
  },
  {
    "productId": "9d06d461-90bf-4559-af85-875221fc0ada",
    "productName": "Fantastic Fresh Keyboard",
    "price": "626.00",
    "productDescription": "The Football Is Good For Training And Recreational Purposes",
    "registeredAt": "2026-02-20T17:20:43.834Z"
  },
  {
    "productId": "37dd98bb-0064-4cfc-98dc-f6bdc7adca9f",
    "productName": "Tasty Plastic Pizza",
    "price": "833.00",
    "productDescription": "The automobile layout consists of a front-engine design, with transaxle-type transmissions mounted at the rear of the engine and four wheel drive",
    "registeredAt": "2026-01-15T03:44:50.025Z"
  },
  {
    "productId": "49e14ad3-3943-4ed3-954b-5d7984e07065",
    "productName": "Ergonomic Plastic Hat",
    "price": "633.00",
    "productDescription": "The automobile layout consists of a front-engine design, with transaxle-type transmissions mounted at the rear of the engine and four wheel drive",
    "registeredAt": "2025-05-16T22:49:01.097Z"
  },
  {
    "productId": "737ae712-b3ff-43a7-8c3f-8cdbbb3978ea",
    "productName": "Electronic Rubber Towels",
    "price": "860.00",
    "productDescription": "The slim & simple Maple Gaming Keyboard from Dev Byte comes with a sleek body and 7- Color RGB LED Back-lighting for smart functionality",
    "registeredAt": "2025-04-21T17:14:53.862Z"
  },
  {
    "productId": "a722fd19-6fd9-4a4b-b967-ccbeddef544d",
    "productName": "Modern Frozen Fish",
    "price": "927.00",
    "productDescription": "Carbonite web goalkeeper gloves are ergonomically designed to give easy fit",
    "registeredAt": "2026-01-29T20:59:21.458Z"
  },
  {
    "productId": "068ddaa0-27db-47fe-8092-db29b43428ff",
    "productName": "Fantastic Plastic Keyboard",
    "price": "102.00",
    "productDescription": "Ergonomic executive chair upholstered in bonded black leather and PVC padded seat and back for all-day comfort and support",
    "registeredAt": "2025-03-30T06:32:34.487Z"
  },
  {
    "productId": "349295f5-3a29-4a4b-8482-e2bf75f29da9",
    "productName": "Luxurious Fresh Computer",
    "price": "910.00",
    "productDescription": "Carbonite web goalkeeper gloves are ergonomically designed to give easy fit",
    "registeredAt": "2025-08-14T12:11:43.201Z"
  },
  {
    "productId": "7faf374d-2b29-4713-b86d-892800be2768",
    "productName": "Incredible Metal Gloves",
    "price": "704.00",
    "productDescription": "Carbonite web goalkeeper gloves are ergonomically designed to give easy fit",
    "registeredAt": "2025-07-16T00:02:08.506Z"
  },
  {
    "productId": "bfa1373d-0995-49c7-8ed5-9310f3d844f2",
    "productName": "Sleek Wooden Computer",
    "price": "18.00",
    "productDescription": "The slim & simple Maple Gaming Keyboard from Dev Byte comes with a sleek body and 7- Color RGB LED Back-lighting for smart functionality",
    "registeredAt": "2025-06-08T00:08:28.206Z"
  },
  {
    "productId": "5d3912e3-9514-474a-9f09-7e1fcff0fc2f",
    "productName": "Bespoke Plastic Towels",
    "price": "263.00",
    "productDescription": "New range of formal shirts are designed keeping you in mind. With fits and styling that will make you stand apart",
    "registeredAt": "2025-05-20T09:55:31.638Z"
  }
]
