[
  {
    "productId": "fcb90831-f4d6-483c-9bdf-fe677f10711c",
    "productName": "Elegant Frozen Hat",
    "price": "663.00",
    "productDescription": "Boston's most advanced compression wear technology increases muscle oxygenation, stabilizes active muscles",
    "registeredAt": "2025-05-28T22:19:26.846Z"
  },
  {
    "productId": "a42a6d0e-01c5-4c84-b03f-b3d7ab70608c",
    "productName": "Handmade Soft Keyboard",
    "price": "278.00",
    "productDescription": "The Football Is Good For Training And Recreational Purposes",
    "registeredAt": "2025-05-21T06:49:11.744Z"
  },
  {
    "productId": "b35dd6fb-4c24-4715-85c8-31a04d3956b5",
    "productName": "Ergonomic Plastic Keyboard",
    "price": "484.00",
    "productDescription": "Carbonite web goalkeeper gloves are ergonomically designed to give easy fit",
    "registeredAt": "2025-06-07T06:44:31.442Z"
  },
  {
    "productId": "26056faf-4bc1-4048-b9e6-770afa941dd6",
    "productName": "Luxurious Steel Mouse",
    "price": "508.00",
    "productDescription": "The Apollotech B340 is an affordable wireless mouse with reliable connectivity, 12 months battery life and modern design",
    "registeredAt": "2025-10-17T23:46:43.847Z"
  },
  {
    "productId": "ab597ef1-8bc4-4469-97e7-64dc30b8c31d",
    "productName": "Licensed Fresh Towels",
    "price": "11.00",
    "productDescription": "The slim & simple Maple Gaming Keyboard from Dev Byte comes with a sleek body and 7- Color RGB LED Back-lighting for smart functionality",
    "registeredAt": "2026-02-20T11:54:46.762Z"
  },
  {
    "productId": "0f24abc6-35e5-40b9-ad21-4ed05a72359a",
    "productName": "Rustic Soft Cheese",
    "price": "731.00",
    "productDescription": "The automobile layout consists of a front-engine design, with transaxle-type transmissions mounted at the rear of the engine and four wheel drive",
    "registeredAt": "2025-05-17T17:16:12.357Z"
  },
  {
    "productId": "3c8a0c95-431a-4687-8cd5-d480e9f63065",
    "productName": "Rustic Frozen Chips",
    "price": "448.00",
    "productDescription": "The automobile layout consists of a front-engine design, with transaxle-type transmissions mounted at the rear of the engine and four wheel drive",
    "registeredAt": "2025-10-25T10:37:40.393Z"
  },
  {
    "productId": "c4770f1f-3afb-4a48-966b-f387993c4124",
    "productName": "Handmade Steel Mouse",
    "price": "265.00",
    "productDescription": "The Apollotech B340 is an affordable wireless mouse with reliable connectivity, 12 months battery life and modern design",
    "registeredAt": "2025-08-10T21:41:45.367Z"
  },
  {
    "productId": "66547dc0-e9fe-43fa-bfad-7c8818009c73",
    "productName": "Sleek Cotton Chicken",
    "price": "242.00",
    "productDescription": "New ABC 13 9370, 13.3, 5th Gen CoreA5-8250U, 8GB RAM, 256GB SSD, power UHD Graphics, OS 10 Home, OS Office A & J 2016",
    "registeredAt": "2025-07-19T00:26:43.410Z"
  },
  {
    "productId": "26f6604b-20db-437e-b046-6d106a0cf57c",
    "productName": "Practical Bronze Keyboard",
    "price": "106.00",
    "productDescription": "Andy shoes are designed to keeping in mind durability as well as trends, the most stylish range of shoes & sandals",
    "registeredAt": "2026-01-23T20:51:29.401Z"
  },
  {
    "productId": "40da71cb-2447-4c82-a9b6-c96ef6f73c91",
    "productName": "Rustic Cotton Chips",
    "price": "647.00",
    "productDescription": "New range of formal shirts are designed keeping you in mind. With fits and styling that will make you stand apart",
    "registeredAt": "2025-07-14T11:59:37.442Z"
  },
  {
    "productId": "435f161f-8f66-4895-9c8f-2575031fcf74",
    "productName": "Unbranded Metal Chicken",
    "price": "357.00",
    "productDescription": "The Apollotech B340 is an affordable wireless mouse with reliable connectivity, 12 months battery life and modern design",
    "registeredAt": "2025-08-05T00:45:43.803Z"
  },
  {
    "productId": "361809a6-90ed-446b-8829-78b530603044",
    "productName": "Gorgeous Concrete Soap",
    "price": "417.00",
    "productDescription": "The Apollotech B340 is an affordable wireless mouse with reliable connectivity, 12 months battery life and modern design",
    "registeredAt": "2026-03-04T14:29:37.656Z"
  },
  {
    "productId": "c06262fc-1076-4418-8c18-068880014809",
    "productName": "Sleek Frozen Soap",
    "price": "204.00",
    "productDescription": "The Apollotech B340 is an affordable wireless mouse with reliable connectivity, 12 months battery life and modern design",
    "registeredAt": "2026-01-11T09:54:15.128Z"
  },
  {
    "productId": "4ab5d2ea-9a91-40ad-8489-48c3eecd8b6e",
    "productName": "Generic Rubber Bacon",
    "price": "119.00",
    "productDescription": "Ergonomic executive chair upholstered in bonded black leather and PVC padded seat and back for all-day comfort and support",
    "registeredAt": "2026-02-02T10:48:14.099Z"
  },
  {
    "productId": "6ea66e60-fad4-44eb-9a9f-cc70a7105667",
    "productName": "Awesome Wooden Chicken",
    "price": "483.00",
    "productDescription": "The slim & simple Maple Gaming Keyboard from Dev Byte comes with a sleek body and 7- Color RGB LED Back-lighting for smart functionality",
    "registeredAt": "2026-02-20T18:37:58.318Z"
  },
  {
    "productId": "36159dac-7a88-4660-abe9-09319b6a03d7",
    "productName": "Licensed Fresh Mouse",
    "price": "112.00",
    "productDescription": "Carbonite web goalkeeper gloves are ergonomically designed to give easy fit",
    "registeredAt": "2025-03-22T01:27:30.873Z"
  },
  {
    "productId": "0a57b4df-0d85-4372-9f37-8212843ec9d8",
    "productName": "Tasty Wooden Bacon",
    "price": "107.00",
    "productDescription": "Andy shoes are designed to keeping in mind durability as well as trends, the most stylish range of shoes & sandals",
    "registeredAt": "2025-07-17T12:38:21.189Z"
  },
  {
    "productId": "4afe6f8a-0dec-4337-9b26-d025d3d210ff",
    "productName": "Recycled Granite Chips",
    "price": "866.00",
    "productDescription": "The automobile layout consists of a front-engine design, with transaxle-type transmissions mounted at the rear of the engine and four wheel drive",
    "registeredAt": "2025-07-27T00:47:09.084Z"
  }
]
